{
  "title": "WH6S on 18.1 MHz",
  "story": [
    {
      "type": "paragraph",
      "text": "These acknowldgements were recorded over 26.2 minutes starting with WH6S at 11/19/2020, 3:50:48 PM. See [[Spark Decodes]]",
      "id": "37804510247"
    },
    {
      "type": "graphviz",
      "text": "strict digraph {\n    layout=neato\n    node [style=filled fillcolor=bisque]\n    \"WH6S\" -> \"HL3EPH\"\n\"JA2QXP\" -> \"KE6GLA\"\n\"HL3EPH\" -> \"WH6S\"\n\"JA8ZO\" -> \"VE6WQ\"\n\"AL7TC\" -> \"XQ3SK\"\n\"N5XJ\" -> \"JM8MGU\"\n\"JA1LSY\" -> \"N6SKM\"\n\"JA8ZO\" -> \"K7CTV\"\n\"WH6S\" -> \"WB6ODR\"\n\"JR7TEQ\" -> \"VA7AMV\"\n\"AL7TC\" -> \"LU8VLE\"\n\"N5XJ\" -> \"JH1CJY\"\n\"N5XJ\" -> \"JH2KKW\"\n\"WH6S\" -> \"KW4FAB\"\n\"JA1LSY\" -> \"WB7DD\"\n\"WH6S\" -> \"PY2DN\"\n\"N5XJ\" -> \"JH7UKE\"\n\"JP1LRT\" -> \"KQ5U\"\n\"XQ3SK\" -> \"KX5W\"\n\"K7GQ\" -> \"VK6YM\"\n\"HL3EPH\" -> \"VE6WQ\"\n\"JA1LSY\" -> \"W5NMG\"\n\"JA1DKT\" -> \"VA7PSK\"\n\"K7GQ\" -> \"JR1WCS\"\n\"JH1KAK\" -> \"K6GZ\"\n\"JR2AMZ\" -> \"KQ5U\"\n\"WH6S\" -> \"JG2JWA\"\n\"JH1LZU\" -> \"VE6WQ\"\n\"HL3EPH\" -> \"KA7ESE\"\n\"JR7TEQ\" -> \"VK6YM\"\n\"K7GQ\" -> \"JR2BYJ\"\n\"JA4VUQ\" -> \"N5XJ\"\n\"JA9CAC\" -> \"VE6WQ\"\n\"HL3EPH\" -> \"VA7AMV\"\n\"AL7TC\" -> \"JA1JXT\"\n\"JH1LZU\" -> \"LU8VLE\"\n\"WH6S\" -> \"PP5TI\"\n\"AL7TC\" -> \"JM8MGU\"\n\"WH6S\" -> \"HK3P\"\n\"AL7TC\" -> \"YB1MIG\"\n\"JH1LZU\" -> \"KJ4GK\"\n\"JR7TEQ\" -> \"VE6YZ\"\n\"JR2BYJ\" -> \"PY5ZHP\"\n\"AL7TC\" -> \"YB1MIG\"\n\"JH1LZU\" -> \"KJ4GK\"\n\"AL7TC\" -> \"YB1MIG\"\n\"JH1LZU\" -> \"KJ4GK\"\n\"AL7TC\" -> \"YB1MIG\"\n\"JA8NDB\" -> \"LU8VLE\"\n\"AL7TC\" -> \"YB1MIG\"\n\"AL7TC\" -> \"YB1MIG\"\n\"JA7QVI\" -> \"HC1KX\"\n\"JP1LRT\" -> \"N7ND\"\n\"JA7QVI\" -> \"HC1KX\"\n\"JA7QVI\" -> \"HC1KX\"\n\"JH8OCV\" -> \"3G3G\"\n\"HL3EPH\" -> \"VE7SA\"\n\"JA7QVI\" -> \"PY2ABA\"\n\"UA0JFG\" -> \"3G3G\"\n\"JH8OCV\" -> \"N5XJ\"\n\"JA7QVI\" -> \"PY2ABA\"\n\"JH8OCV\" -> \"N5XJ\"\n\"JA7QVI\" -> \"PY2ABA\"\n\"JA1DKT\" -> \"N5XJ\"\n\"JH8OCV\" -> \"N5XJ\"\n\"HL3EPH\" -> \"VE7XT\"\n\"JH8OCV\" -> \"N5XJ\"\n\"JR7GBL\" -> \"PY5ZHP\"\n\"JA7QVI\" -> \"N7ND\"\n\"WH6S\" -> \"KB7FD\"\n\"JA7QVI\" -> \"HC1Y\"\n\"HL3EPH\" -> \"AA4M\"\n\"JA7QVI\" -> \"HC1Y\"\n\"JA7QVI\" -> \"HC1Y\"\n\"JH2WDT\" -> \"KB7FD\"\n\"JA7QVI\" -> \"HC1Y\"\n\"WH6S\" -> \"PY2KS\"\n\"JR3UIC\" -> \"AA4M\"\n\"JH2WDT\" -> \"K7CTV\"\n\"WH6S\" -> \"PY2ABA\"}",
      "id": "531244108961",
      "dot": "strict digraph {\n    layout=neato\n    node [style=filled fillcolor=bisque]\n    \"WH6S\" -> \"HL3EPH\"\n\"JA2QXP\" -> \"KE6GLA\"\n\"HL3EPH\" -> \"WH6S\"\n\"JA8ZO\" -> \"VE6WQ\"\n\"AL7TC\" -> \"XQ3SK\"\n\"N5XJ\" -> \"JM8MGU\"\n\"JA1LSY\" -> \"N6SKM\"\n\"JA8ZO\" -> \"K7CTV\"\n\"WH6S\" -> \"WB6ODR\"\n\"JR7TEQ\" -> \"VA7AMV\"\n\"AL7TC\" -> \"LU8VLE\"\n\"N5XJ\" -> \"JH1CJY\"\n\"N5XJ\" -> \"JH2KKW\"\n\"WH6S\" -> \"KW4FAB\"\n\"JA1LSY\" -> \"WB7DD\"\n\"WH6S\" -> \"PY2DN\"\n\"N5XJ\" -> \"JH7UKE\"\n\"JP1LRT\" -> \"KQ5U\"\n\"XQ3SK\" -> \"KX5W\"\n\"K7GQ\" -> \"VK6YM\"\n\"HL3EPH\" -> \"VE6WQ\"\n\"JA1LSY\" -> \"W5NMG\"\n\"JA1DKT\" -> \"VA7PSK\"\n\"K7GQ\" -> \"JR1WCS\"\n\"JH1KAK\" -> \"K6GZ\"\n\"JR2AMZ\" -> \"KQ5U\"\n\"WH6S\" -> \"JG2JWA\"\n\"JH1LZU\" -> \"VE6WQ\"\n\"HL3EPH\" -> \"KA7ESE\"\n\"JR7TEQ\" -> \"VK6YM\"\n\"K7GQ\" -> \"JR2BYJ\"\n\"JA4VUQ\" -> \"N5XJ\"\n\"JA9CAC\" -> \"VE6WQ\"\n\"HL3EPH\" -> \"VA7AMV\"\n\"AL7TC\" -> \"JA1JXT\"\n\"JH1LZU\" -> \"LU8VLE\"\n\"WH6S\" -> \"PP5TI\"\n\"AL7TC\" -> \"JM8MGU\"\n\"WH6S\" -> \"HK3P\"\n\"AL7TC\" -> \"YB1MIG\"\n\"JH1LZU\" -> \"KJ4GK\"\n\"JR7TEQ\" -> \"VE6YZ\"\n\"JR2BYJ\" -> \"PY5ZHP\"\n\"AL7TC\" -> \"YB1MIG\"\n\"JH1LZU\" -> \"KJ4GK\"\n\"AL7TC\" -> \"YB1MIG\"\n\"JH1LZU\" -> \"KJ4GK\"\n\"AL7TC\" -> \"YB1MIG\"\n\"JA8NDB\" -> \"LU8VLE\"\n\"AL7TC\" -> \"YB1MIG\"\n\"AL7TC\" -> \"YB1MIG\"\n\"JA7QVI\" -> \"HC1KX\"\n\"JP1LRT\" -> \"N7ND\"\n\"JA7QVI\" -> \"HC1KX\"\n\"JA7QVI\" -> \"HC1KX\"\n\"JH8OCV\" -> \"3G3G\"\n\"HL3EPH\" -> \"VE7SA\"\n\"JA7QVI\" -> \"PY2ABA\"\n\"UA0JFG\" -> \"3G3G\"\n\"JH8OCV\" -> \"N5XJ\"\n\"JA7QVI\" -> \"PY2ABA\"\n\"JH8OCV\" -> \"N5XJ\"\n\"JA7QVI\" -> \"PY2ABA\"\n\"JA1DKT\" -> \"N5XJ\"\n\"JH8OCV\" -> \"N5XJ\"\n\"HL3EPH\" -> \"VE7XT\"\n\"JH8OCV\" -> \"N5XJ\"\n\"JR7GBL\" -> \"PY5ZHP\"\n\"JA7QVI\" -> \"N7ND\"\n\"WH6S\" -> \"KB7FD\"\n\"JA7QVI\" -> \"HC1Y\"\n\"HL3EPH\" -> \"AA4M\"\n\"JA7QVI\" -> \"HC1Y\"\n\"JA7QVI\" -> \"HC1Y\"\n\"JH2WDT\" -> \"KB7FD\"\n\"JA7QVI\" -> \"HC1Y\"\n\"WH6S\" -> \"PY2KS\"\n\"JR3UIC\" -> \"AA4M\"\n\"JH2WDT\" -> \"K7CTV\"\n\"WH6S\" -> \"PY2ABA\"}",
      "svg": "<?xml version=\"1.0\" encoding=\"UTF-8\" standalone=\"no\"?>\n<!DOCTYPE svg PUBLIC \"-//W3C//DTD SVG 1.1//EN\"\n \"http://www.w3.org/Graphics/SVG/1.1/DTD/svg11.dtd\">\n<!-- Generated by graphviz version 2.44.0 (20200518.1210)\n -->\n<!-- Pages: 1 -->\n<svg width=\"1312pt\" height=\"1116pt\"\n viewBox=\"0.00 0.00 1311.79 1116.11\" xmlns=\"http://www.w3.org/2000/svg\" xmlns:xlink=\"http://www.w3.org/1999/xlink\">\n<g id=\"graph0\" class=\"graph\" transform=\"scale(1 1) rotate(0) translate(4 1112.11)\">\n<polygon fill=\"white\" stroke=\"transparent\" points=\"-4,4 -4,-1112.11 1307.79,-1112.11 1307.79,4 -4,4\"/>\n<!-- WH6S -->\n<g id=\"node1\" class=\"node\">\n<title>WH6S</title>\n<ellipse fill=\"bisque\" stroke=\"black\" cx=\"524.22\" cy=\"-561.93\" rx=\"37.14\" ry=\"18\"/>\n<text text-anchor=\"middle\" x=\"524.22\" y=\"-557.73\" font-family=\"Times,serif\" font-size=\"14.00\">WH6S</text>\n</g>\n<!-- HL3EPH -->\n<g id=\"node2\" class=\"node\">\n<title>HL3EPH</title>\n<ellipse fill=\"bisque\" stroke=\"black\" cx=\"611.71\" cy=\"-587.61\" rx=\"46.95\" ry=\"18\"/>\n<text text-anchor=\"middle\" x=\"611.71\" y=\"-583.41\" font-family=\"Times,serif\" font-size=\"14.00\">HL3EPH</text>\n</g>\n<!-- WH6S&#45;&gt;HL3EPH -->\n<g id=\"edge1\" class=\"edge\">\n<title>WH6S&#45;&gt;HL3EPH</title>\n<path fill=\"none\" stroke=\"black\" d=\"M548.71,-575.63C551.54,-576.64 554.5,-577.64 557.53,-578.62\"/>\n<polygon fill=\"black\" stroke=\"black\" points=\"556.79,-582.06 567.38,-581.63 558.84,-575.36 556.79,-582.06\"/>\n</g>\n<!-- WB6ODR -->\n<g id=\"node14\" class=\"node\">\n<title>WB6ODR</title>\n<ellipse fill=\"bisque\" stroke=\"black\" cx=\"508.53\" cy=\"-468.48\" rx=\"51.61\" ry=\"18\"/>\n<text text-anchor=\"middle\" x=\"508.53\" y=\"-464.28\" font-family=\"Times,serif\" font-size=\"14.00\">WB6ODR</text>\n</g>\n<!-- WH6S&#45;&gt;WB6ODR -->\n<g id=\"edge9\" class=\"edge\">\n<title>WH6S&#45;&gt;WB6ODR</title>\n<path fill=\"none\" stroke=\"black\" d=\"M521.19,-543.91C518.95,-530.55 515.85,-512.09 513.27,-496.77\"/>\n<polygon fill=\"black\" stroke=\"black\" points=\"516.7,-496.05 511.6,-486.77 509.8,-497.21 516.7,-496.05\"/>\n</g>\n<!-- KW4FAB -->\n<g id=\"node20\" class=\"node\">\n<title>KW4FAB</title>\n<ellipse fill=\"bisque\" stroke=\"black\" cx=\"470.09\" cy=\"-488.91\" rx=\"50.96\" ry=\"18\"/>\n<text text-anchor=\"middle\" x=\"470.09\" y=\"-484.71\" font-family=\"Times,serif\" font-size=\"14.00\">KW4FAB</text>\n</g>\n<!-- WH6S&#45;&gt;KW4FAB -->\n<g id=\"edge14\" class=\"edge\">\n<title>WH6S&#45;&gt;KW4FAB</title>\n<path fill=\"none\" stroke=\"black\" d=\"M511.39,-544.63C504.7,-535.6 496.38,-524.38 488.97,-514.38\"/>\n<polygon fill=\"black\" stroke=\"black\" points=\"491.78,-512.3 483.01,-506.35 486.15,-516.46 491.78,-512.3\"/>\n</g>\n<!-- PY2DN -->\n<g id=\"node22\" class=\"node\">\n<title>PY2DN</title>\n<ellipse fill=\"bisque\" stroke=\"black\" cx=\"515.35\" cy=\"-502.84\" rx=\"42.3\" ry=\"18\"/>\n<text text-anchor=\"middle\" x=\"515.35\" y=\"-498.64\" font-family=\"Times,serif\" font-size=\"14.00\">PY2DN</text>\n</g>\n<!-- WH6S&#45;&gt;PY2DN -->\n<g id=\"edge16\" class=\"edge\">\n<title>WH6S&#45;&gt;PY2DN</title>\n<path fill=\"none\" stroke=\"black\" d=\"M521.51,-543.88C520.9,-539.83 520.24,-535.44 519.59,-531.09\"/>\n<polygon fill=\"black\" stroke=\"black\" points=\"523.05,-530.55 518.1,-521.18 516.13,-531.59 523.05,-530.55\"/>\n</g>\n<!-- JG2JWA -->\n<g id=\"node36\" class=\"node\">\n<title>JG2JWA</title>\n<ellipse fill=\"bisque\" stroke=\"black\" cx=\"478.01\" cy=\"-632.86\" rx=\"46.37\" ry=\"18\"/>\n<text text-anchor=\"middle\" x=\"478.01\" y=\"-628.66\" font-family=\"Times,serif\" font-size=\"14.00\">JG2JWA</text>\n</g>\n<!-- WH6S&#45;&gt;JG2JWA -->\n<g id=\"edge27\" class=\"edge\">\n<title>WH6S&#45;&gt;JG2JWA</title>\n<path fill=\"none\" stroke=\"black\" d=\"M512.79,-579.46C507.5,-587.59 501.1,-597.41 495.24,-606.41\"/>\n<polygon fill=\"black\" stroke=\"black\" points=\"492.15,-604.75 489.62,-615.04 498.01,-608.57 492.15,-604.75\"/>\n</g>\n<!-- PP5TI -->\n<g id=\"node43\" class=\"node\">\n<title>PP5TI</title>\n<ellipse fill=\"bisque\" stroke=\"black\" cx=\"509.58\" cy=\"-631.63\" rx=\"35.93\" ry=\"18\"/>\n<text text-anchor=\"middle\" x=\"509.58\" y=\"-627.43\" font-family=\"Times,serif\" font-size=\"14.00\">PP5TI</text>\n</g>\n<!-- WH6S&#45;&gt;PP5TI -->\n<g id=\"edge37\" class=\"edge\">\n<title>WH6S&#45;&gt;PP5TI</title>\n<path fill=\"none\" stroke=\"black\" d=\"M520.45,-579.88C518.94,-587.06 517.17,-595.5 515.5,-603.46\"/>\n<polygon fill=\"black\" stroke=\"black\" points=\"512.02,-602.99 513.39,-613.5 518.87,-604.43 512.02,-602.99\"/>\n</g>\n<!-- HK3P -->\n<g id=\"node44\" class=\"node\">\n<title>HK3P</title>\n<ellipse fill=\"bisque\" stroke=\"black\" cx=\"457.86\" cy=\"-526.5\" rx=\"35.35\" ry=\"18\"/>\n<text text-anchor=\"middle\" x=\"457.86\" y=\"-522.3\" font-family=\"Times,serif\" font-size=\"14.00\">HK3P</text>\n</g>\n<!-- WH6S&#45;&gt;HK3P -->\n<g id=\"edge39\" class=\"edge\">\n<title>WH6S&#45;&gt;HK3P</title>\n<path fill=\"none\" stroke=\"black\" d=\"M499.13,-548.53C496.67,-547.22 494.14,-545.87 491.61,-544.52\"/>\n<polygon fill=\"black\" stroke=\"black\" points=\"493.01,-541.3 482.54,-539.68 489.71,-547.47 493.01,-541.3\"/>\n</g>\n<!-- PY2ABA -->\n<g id=\"node56\" class=\"node\">\n<title>PY2ABA</title>\n<ellipse fill=\"bisque\" stroke=\"black\" cx=\"425.36\" cy=\"-590.43\" rx=\"48.68\" ry=\"18\"/>\n<text text-anchor=\"middle\" x=\"425.36\" y=\"-586.23\" font-family=\"Times,serif\" font-size=\"14.00\">PY2ABA</text>\n</g>\n<!-- WH6S&#45;&gt;PY2ABA -->\n<g id=\"edge63\" class=\"edge\">\n<title>WH6S&#45;&gt;PY2ABA</title>\n<path fill=\"none\" stroke=\"black\" d=\"M492.12,-571.18C486.2,-572.89 479.9,-574.71 473.63,-576.52\"/>\n<polygon fill=\"black\" stroke=\"black\" points=\"472.48,-573.2 463.85,-579.34 474.42,-579.93 472.48,-573.2\"/>\n</g>\n<!-- KB7FD -->\n<g id=\"node60\" class=\"node\">\n<title>KB7FD</title>\n<ellipse fill=\"bisque\" stroke=\"black\" cx=\"570.59\" cy=\"-498.71\" rx=\"41.73\" ry=\"18\"/>\n<text text-anchor=\"middle\" x=\"570.59\" y=\"-494.51\" font-family=\"Times,serif\" font-size=\"14.00\">KB7FD</text>\n</g>\n<!-- WH6S&#45;&gt;KB7FD -->\n<g id=\"edge56\" class=\"edge\">\n<title>WH6S&#45;&gt;KB7FD</title>\n<path fill=\"none\" stroke=\"black\" d=\"M536.89,-544.66C541.49,-538.38 546.79,-531.16 551.81,-524.32\"/>\n<polygon fill=\"black\" stroke=\"black\" points=\"554.84,-526.1 557.93,-515.96 549.2,-521.96 554.84,-526.1\"/>\n</g>\n<!-- PY2KS -->\n<g id=\"node64\" class=\"node\">\n<title>PY2KS</title>\n<ellipse fill=\"bisque\" stroke=\"black\" cx=\"471.31\" cy=\"-577.55\" rx=\"40.59\" ry=\"18\"/>\n<text text-anchor=\"middle\" x=\"471.31\" y=\"-573.35\" font-family=\"Times,serif\" font-size=\"14.00\">PY2KS</text>\n</g>\n<!-- WH6S&#45;&gt;PY2KS -->\n<g id=\"edge60\" class=\"edge\">\n<title>WH6S&#45;&gt;PY2KS</title>\n<path fill=\"none\" stroke=\"black\" d=\"M492.22,-571.38C492.18,-571.39 492.13,-571.4 492.09,-571.41\"/>\n<polygon fill=\"black\" stroke=\"black\" points=\"500.56,-565.26 491.96,-571.45 502.54,-571.97 500.56,-565.26\"/>\n</g>\n<!-- HL3EPH&#45;&gt;WH6S -->\n<g id=\"edge3\" class=\"edge\">\n<title>HL3EPH&#45;&gt;WH6S</title>\n<path fill=\"none\" stroke=\"black\" d=\"M584.38,-572.92C579.96,-571.39 575.27,-569.89 570.55,-568.49\"/>\n<polygon fill=\"black\" stroke=\"black\" points=\"571.43,-565.11 560.86,-565.78 569.55,-571.85 571.43,-565.11\"/>\n</g>\n<!-- VE6WQ -->\n<g id=\"node6\" class=\"node\">\n<title>VE6WQ</title>\n<ellipse fill=\"bisque\" stroke=\"black\" cx=\"699.32\" cy=\"-646.19\" rx=\"44.65\" ry=\"18\"/>\n<text text-anchor=\"middle\" x=\"699.32\" y=\"-641.99\" font-family=\"Times,serif\" font-size=\"14.00\">VE6WQ</text>\n</g>\n<!-- HL3EPH&#45;&gt;VE6WQ -->\n<g id=\"edge21\" class=\"edge\">\n<title>HL3EPH&#45;&gt;VE6WQ</title>\n<path fill=\"none\" stroke=\"black\" d=\"M635.19,-603.31C645.19,-610 657,-617.9 667.75,-625.08\"/>\n<polygon fill=\"black\" stroke=\"black\" points=\"665.83,-628.01 676.08,-630.66 669.72,-622.19 665.83,-628.01\"/>\n</g>\n<!-- VA7AMV -->\n<g id=\"node16\" class=\"node\">\n<title>VA7AMV</title>\n<ellipse fill=\"bisque\" stroke=\"black\" cx=\"660.61\" cy=\"-494.69\" rx=\"52.17\" ry=\"18\"/>\n<text text-anchor=\"middle\" x=\"660.61\" y=\"-490.49\" font-family=\"Times,serif\" font-size=\"14.00\">VA7AMV</text>\n</g>\n<!-- HL3EPH&#45;&gt;VA7AMV -->\n<g id=\"edge34\" class=\"edge\">\n<title>HL3EPH&#45;&gt;VA7AMV</title>\n<path fill=\"none\" stroke=\"black\" d=\"M621.14,-569.7C628.31,-556.07 638.29,-537.1 646.43,-521.64\"/>\n<polygon fill=\"black\" stroke=\"black\" points=\"649.65,-523.03 651.21,-512.55 643.46,-519.77 649.65,-523.03\"/>\n</g>\n<!-- KA7ESE -->\n<g id=\"node38\" class=\"node\">\n<title>KA7ESE</title>\n<ellipse fill=\"bisque\" stroke=\"black\" cx=\"663.31\" cy=\"-554.87\" rx=\"46.95\" ry=\"18\"/>\n<text text-anchor=\"middle\" x=\"663.31\" y=\"-550.67\" font-family=\"Times,serif\" font-size=\"14.00\">KA7ESE</text>\n</g>\n<!-- HL3EPH&#45;&gt;KA7ESE -->\n<g id=\"edge29\" class=\"edge\">\n<title>HL3EPH&#45;&gt;KA7ESE</title>\n<path fill=\"none\" stroke=\"black\" d=\"M636,-572.2C636.12,-572.13 636.24,-572.05 636.35,-571.98\"/>\n<polygon fill=\"black\" stroke=\"black\" points=\"632.26,-578.72 638.83,-570.41 628.51,-572.81 632.26,-578.72\"/>\n</g>\n<!-- VE7SA -->\n<g id=\"node55\" class=\"node\">\n<title>VE7SA</title>\n<ellipse fill=\"bisque\" stroke=\"black\" cx=\"655.13\" cy=\"-606.54\" rx=\"41.15\" ry=\"18\"/>\n<text text-anchor=\"middle\" x=\"655.13\" y=\"-602.34\" font-family=\"Times,serif\" font-size=\"14.00\">VE7SA</text>\n</g>\n<!-- HL3EPH&#45;&gt;VE7SA -->\n<g id=\"edge48\" class=\"edge\">\n<title>HL3EPH&#45;&gt;VE7SA</title>\n<path fill=\"none\" stroke=\"black\" d=\"M642.81,-601.17C642.86,-601.19 642.91,-601.21 642.97,-601.24\"/>\n<polygon fill=\"black\" stroke=\"black\" points=\"632.56,-600.52 643.13,-601.31 635.36,-594.1 632.56,-600.52\"/>\n</g>\n<!-- VE7XT -->\n<g id=\"node58\" class=\"node\">\n<title>VE7XT</title>\n<ellipse fill=\"bisque\" stroke=\"black\" cx=\"604.7\" cy=\"-643.27\" rx=\"41.71\" ry=\"18\"/>\n<text text-anchor=\"middle\" x=\"604.7\" y=\"-639.07\" font-family=\"Times,serif\" font-size=\"14.00\">VE7XT</text>\n</g>\n<!-- HL3EPH&#45;&gt;VE7XT -->\n<g id=\"edge53\" class=\"edge\">\n<title>HL3EPH&#45;&gt;VE7XT</title>\n<path fill=\"none\" stroke=\"black\" d=\"M609.42,-605.84C609.04,-608.85 608.64,-612.03 608.23,-615.21\"/>\n<polygon fill=\"black\" stroke=\"black\" points=\"604.75,-614.83 606.98,-625.19 611.7,-615.71 604.75,-614.83\"/>\n</g>\n<!-- AA4M -->\n<g id=\"node62\" class=\"node\">\n<title>AA4M</title>\n<ellipse fill=\"bisque\" stroke=\"black\" cx=\"579.05\" cy=\"-676.24\" rx=\"38.28\" ry=\"18\"/>\n<text text-anchor=\"middle\" x=\"579.05\" y=\"-672.04\" font-family=\"Times,serif\" font-size=\"14.00\">AA4M</text>\n</g>\n<!-- HL3EPH&#45;&gt;AA4M -->\n<g id=\"edge58\" class=\"edge\">\n<title>HL3EPH&#45;&gt;AA4M</title>\n<path fill=\"none\" stroke=\"black\" d=\"M605.1,-605.55C600.54,-617.92 594.39,-634.61 589.21,-648.66\"/>\n<polygon fill=\"black\" stroke=\"black\" points=\"585.82,-647.74 585.65,-658.33 592.39,-650.16 585.82,-647.74\"/>\n</g>\n<!-- JA2QXP -->\n<g id=\"node3\" class=\"node\">\n<title>JA2QXP</title>\n<ellipse fill=\"bisque\" stroke=\"black\" cx=\"969.9\" cy=\"-754.64\" rx=\"45.81\" ry=\"18\"/>\n<text text-anchor=\"middle\" x=\"969.9\" y=\"-750.44\" font-family=\"Times,serif\" font-size=\"14.00\">JA2QXP</text>\n</g>\n<!-- KE6GLA -->\n<g id=\"node4\" class=\"node\">\n<title>KE6GLA</title>\n<ellipse fill=\"bisque\" stroke=\"black\" cx=\"1041.11\" cy=\"-744\" rx=\"48.66\" ry=\"18\"/>\n<text text-anchor=\"middle\" x=\"1041.11\" y=\"-739.8\" font-family=\"Times,serif\" font-size=\"14.00\">KE6GLA</text>\n</g>\n<!-- JA2QXP&#45;&gt;KE6GLA -->\n<g id=\"edge2\" class=\"edge\">\n<title>JA2QXP&#45;&gt;KE6GLA</title>\n<path fill=\"none\" stroke=\"black\" d=\"M1012.97,-748.2C1013.03,-748.2 1013.09,-748.19 1013.14,-748.18\"/>\n<polygon fill=\"black\" stroke=\"black\" points=\"1003.95,-753.1 1013.32,-748.15 1002.91,-746.17 1003.95,-753.1\"/>\n</g>\n<!-- JA8ZO -->\n<g id=\"node5\" class=\"node\">\n<title>JA8ZO</title>\n<ellipse fill=\"bisque\" stroke=\"black\" cx=\"759.81\" cy=\"-589.08\" rx=\"39.43\" ry=\"18\"/>\n<text text-anchor=\"middle\" x=\"759.81\" y=\"-584.88\" font-family=\"Times,serif\" font-size=\"14.00\">JA8ZO</text>\n</g>\n<!-- JA8ZO&#45;&gt;VE6WQ -->\n<g id=\"edge4\" class=\"edge\">\n<title>JA8ZO&#45;&gt;VE6WQ</title>\n<path fill=\"none\" stroke=\"black\" d=\"M742.64,-605.3C737.04,-610.58 730.7,-616.57 724.63,-622.3\"/>\n<polygon fill=\"black\" stroke=\"black\" points=\"722.04,-619.93 717.17,-629.34 726.84,-625.02 722.04,-619.93\"/>\n</g>\n<!-- K7CTV -->\n<g id=\"node13\" class=\"node\">\n<title>K7CTV</title>\n<ellipse fill=\"bisque\" stroke=\"black\" cx=\"746.72\" cy=\"-510.51\" rx=\"42.3\" ry=\"18\"/>\n<text text-anchor=\"middle\" x=\"746.72\" y=\"-506.31\" font-family=\"Times,serif\" font-size=\"14.00\">K7CTV</text>\n</g>\n<!-- JA8ZO&#45;&gt;K7CTV -->\n<g id=\"edge8\" class=\"edge\">\n<title>JA8ZO&#45;&gt;K7CTV</title>\n<path fill=\"none\" stroke=\"black\" d=\"M756.78,-570.86C755.19,-561.34 753.21,-549.48 751.43,-538.79\"/>\n<polygon fill=\"black\" stroke=\"black\" points=\"754.83,-537.92 749.74,-528.63 747.93,-539.07 754.83,-537.92\"/>\n</g>\n<!-- AL7TC -->\n<g id=\"node7\" class=\"node\">\n<title>AL7TC</title>\n<ellipse fill=\"bisque\" stroke=\"black\" cx=\"843.79\" cy=\"-863.69\" rx=\"41.15\" ry=\"18\"/>\n<text text-anchor=\"middle\" x=\"843.79\" y=\"-859.49\" font-family=\"Times,serif\" font-size=\"14.00\">AL7TC</text>\n</g>\n<!-- XQ3SK -->\n<g id=\"node8\" class=\"node\">\n<title>XQ3SK</title>\n<ellipse fill=\"bisque\" stroke=\"black\" cx=\"794.39\" cy=\"-959.64\" rx=\"42.3\" ry=\"18\"/>\n<text text-anchor=\"middle\" x=\"794.39\" y=\"-955.44\" font-family=\"Times,serif\" font-size=\"14.00\">XQ3SK</text>\n</g>\n<!-- AL7TC&#45;&gt;XQ3SK -->\n<g id=\"edge5\" class=\"edge\">\n<title>AL7TC&#45;&gt;XQ3SK</title>\n<path fill=\"none\" stroke=\"black\" d=\"M834.73,-881.29C827.32,-895.67 816.73,-916.24 808.26,-932.7\"/>\n<polygon fill=\"black\" stroke=\"black\" points=\"805.03,-931.34 803.56,-941.83 811.25,-934.54 805.03,-931.34\"/>\n</g>\n<!-- JM8MGU -->\n<g id=\"node10\" class=\"node\">\n<title>JM8MGU</title>\n<ellipse fill=\"bisque\" stroke=\"black\" cx=\"933.88\" cy=\"-874.12\" rx=\"50.96\" ry=\"18\"/>\n<text text-anchor=\"middle\" x=\"933.88\" y=\"-869.92\" font-family=\"Times,serif\" font-size=\"14.00\">JM8MGU</text>\n</g>\n<!-- AL7TC&#45;&gt;JM8MGU -->\n<g id=\"edge38\" class=\"edge\">\n<title>AL7TC&#45;&gt;JM8MGU</title>\n<path fill=\"none\" stroke=\"black\" d=\"M883.56,-868.3C883.73,-868.32 883.9,-868.34 884.06,-868.36\"/>\n<polygon fill=\"black\" stroke=\"black\" points=\"875.21,-870.86 885.55,-868.53 876.02,-863.9 875.21,-870.86\"/>\n</g>\n<!-- LU8VLE -->\n<g id=\"node17\" class=\"node\">\n<title>LU8VLE</title>\n<ellipse fill=\"bisque\" stroke=\"black\" cx=\"792.35\" cy=\"-793.17\" rx=\"47.51\" ry=\"18\"/>\n<text text-anchor=\"middle\" x=\"792.35\" y=\"-788.97\" font-family=\"Times,serif\" font-size=\"14.00\">LU8VLE</text>\n</g>\n<!-- AL7TC&#45;&gt;LU8VLE -->\n<g id=\"edge11\" class=\"edge\">\n<title>AL7TC&#45;&gt;LU8VLE</title>\n<path fill=\"none\" stroke=\"black\" d=\"M831.07,-846.26C825.12,-838.1 817.91,-828.21 811.33,-819.19\"/>\n<polygon fill=\"black\" stroke=\"black\" points=\"814,-816.91 805.28,-810.9 808.34,-821.04 814,-816.91\"/>\n</g>\n<!-- JA1JXT -->\n<g id=\"node42\" class=\"node\">\n<title>JA1JXT</title>\n<ellipse fill=\"bisque\" stroke=\"black\" cx=\"795.34\" cy=\"-913.45\" rx=\"43.44\" ry=\"18\"/>\n<text text-anchor=\"middle\" x=\"795.34\" y=\"-909.25\" font-family=\"Times,serif\" font-size=\"14.00\">JA1JXT</text>\n</g>\n<!-- AL7TC&#45;&gt;JA1JXT -->\n<g id=\"edge35\" class=\"edge\">\n<title>AL7TC&#45;&gt;JA1JXT</title>\n<path fill=\"none\" stroke=\"black\" d=\"M827.66,-880.26C824.89,-883.11 821.96,-886.12 819.04,-889.12\"/>\n<polygon fill=\"black\" stroke=\"black\" points=\"816.37,-886.84 811.9,-896.45 821.38,-891.72 816.37,-886.84\"/>\n</g>\n<!-- YB1MIG -->\n<g id=\"node45\" class=\"node\">\n<title>YB1MIG</title>\n<ellipse fill=\"bisque\" stroke=\"black\" cx=\"854.39\" cy=\"-923.25\" rx=\"48.09\" ry=\"18\"/>\n<text text-anchor=\"middle\" x=\"854.39\" y=\"-919.05\" font-family=\"Times,serif\" font-size=\"14.00\">YB1MIG</text>\n</g>\n<!-- AL7TC&#45;&gt;YB1MIG -->\n<g id=\"edge40\" class=\"edge\">\n<title>AL7TC&#45;&gt;YB1MIG</title>\n<path fill=\"none\" stroke=\"black\" d=\"M847.03,-881.89C847.77,-886.04 848.57,-890.55 849.36,-895.02\"/>\n<polygon fill=\"black\" stroke=\"black\" points=\"845.97,-895.94 851.17,-905.17 852.86,-894.71 845.97,-895.94\"/>\n</g>\n<!-- KX5W -->\n<g id=\"node26\" class=\"node\">\n<title>KX5W</title>\n<ellipse fill=\"bisque\" stroke=\"black\" cx=\"759.81\" cy=\"-1035.52\" rx=\"38.85\" ry=\"18\"/>\n<text text-anchor=\"middle\" x=\"759.81\" y=\"-1031.32\" font-family=\"Times,serif\" font-size=\"14.00\">KX5W</text>\n</g>\n<!-- XQ3SK&#45;&gt;KX5W -->\n<g id=\"edge19\" class=\"edge\">\n<title>XQ3SK&#45;&gt;KX5W</title>\n<path fill=\"none\" stroke=\"black\" d=\"M786.2,-977.62C782.02,-986.79 776.85,-998.13 772.2,-1008.33\"/>\n<polygon fill=\"black\" stroke=\"black\" points=\"768.91,-1007.11 767.94,-1017.66 775.28,-1010.02 768.91,-1007.11\"/>\n</g>\n<!-- N5XJ -->\n<g id=\"node9\" class=\"node\">\n<title>N5XJ</title>\n<ellipse fill=\"bisque\" stroke=\"black\" cx=\"1013.78\" cy=\"-913.45\" rx=\"33.63\" ry=\"18\"/>\n<text text-anchor=\"middle\" x=\"1013.78\" y=\"-909.25\" font-family=\"Times,serif\" font-size=\"14.00\">N5XJ</text>\n</g>\n<!-- N5XJ&#45;&gt;JM8MGU -->\n<g id=\"edge6\" class=\"edge\">\n<title>N5XJ&#45;&gt;JM8MGU</title>\n<path fill=\"none\" stroke=\"black\" d=\"M988.94,-901.22C983.83,-898.71 978.34,-896 972.87,-893.31\"/>\n<polygon fill=\"black\" stroke=\"black\" points=\"974.28,-890.11 963.76,-888.83 971.19,-896.39 974.28,-890.11\"/>\n</g>\n<!-- JH1CJY -->\n<g id=\"node18\" class=\"node\">\n<title>JH1CJY</title>\n<ellipse fill=\"bisque\" stroke=\"black\" cx=\"1047.13\" cy=\"-844.89\" rx=\"43.52\" ry=\"18\"/>\n<text text-anchor=\"middle\" x=\"1047.13\" y=\"-840.69\" font-family=\"Times,serif\" font-size=\"14.00\">JH1CJY</text>\n</g>\n<!-- N5XJ&#45;&gt;JH1CJY -->\n<g id=\"edge12\" class=\"edge\">\n<title>N5XJ&#45;&gt;JH1CJY</title>\n<path fill=\"none\" stroke=\"black\" d=\"M1022.37,-895.79C1025.92,-888.49 1030.12,-879.86 1034.04,-871.8\"/>\n<polygon fill=\"black\" stroke=\"black\" points=\"1037.23,-873.24 1038.46,-862.72 1030.94,-870.18 1037.23,-873.24\"/>\n</g>\n<!-- JH2KKW -->\n<g id=\"node19\" class=\"node\">\n<title>JH2KKW</title>\n<ellipse fill=\"bisque\" stroke=\"black\" cx=\"1064.3\" cy=\"-969.49\" rx=\"49.8\" ry=\"18\"/>\n<text text-anchor=\"middle\" x=\"1064.3\" y=\"-965.29\" font-family=\"Times,serif\" font-size=\"14.00\">JH2KKW</text>\n</g>\n<!-- N5XJ&#45;&gt;JH2KKW -->\n<g id=\"edge13\" class=\"edge\">\n<title>N5XJ&#45;&gt;JH2KKW</title>\n<path fill=\"none\" stroke=\"black\" d=\"M1028.39,-929.66C1032.6,-934.32 1037.29,-939.53 1041.86,-944.59\"/>\n<polygon fill=\"black\" stroke=\"black\" points=\"1039.55,-947.26 1048.84,-952.34 1044.75,-942.57 1039.55,-947.26\"/>\n</g>\n<!-- JH7UKE -->\n<g id=\"node23\" class=\"node\">\n<title>JH7UKE</title>\n<ellipse fill=\"bisque\" stroke=\"black\" cx=\"984.39\" cy=\"-981.11\" rx=\"46.37\" ry=\"18\"/>\n<text text-anchor=\"middle\" x=\"984.39\" y=\"-976.91\" font-family=\"Times,serif\" font-size=\"14.00\">JH7UKE</text>\n</g>\n<!-- N5XJ&#45;&gt;JH7UKE -->\n<g id=\"edge17\" class=\"edge\">\n<title>N5XJ&#45;&gt;JH7UKE</title>\n<path fill=\"none\" stroke=\"black\" d=\"M1006.06,-931.22C1003.05,-938.16 999.53,-946.27 996.21,-953.91\"/>\n<polygon fill=\"black\" stroke=\"black\" points=\"992.94,-952.65 992.17,-963.21 999.36,-955.43 992.94,-952.65\"/>\n</g>\n<!-- JA1LSY -->\n<g id=\"node11\" class=\"node\">\n<title>JA1LSY</title>\n<ellipse fill=\"bisque\" stroke=\"black\" cx=\"1019.39\" cy=\"-419.71\" rx=\"44.66\" ry=\"18\"/>\n<text text-anchor=\"middle\" x=\"1019.39\" y=\"-415.51\" font-family=\"Times,serif\" font-size=\"14.00\">JA1LSY</text>\n</g>\n<!-- N6SKM -->\n<g id=\"node12\" class=\"node\">\n<title>N6SKM</title>\n<ellipse fill=\"bisque\" stroke=\"black\" cx=\"1095.27\" cy=\"-431.49\" rx=\"43.52\" ry=\"18\"/>\n<text text-anchor=\"middle\" x=\"1095.27\" y=\"-427.29\" font-family=\"Times,serif\" font-size=\"14.00\">N6SKM</text>\n</g>\n<!-- JA1LSY&#45;&gt;N6SKM -->\n<g id=\"edge7\" class=\"edge\">\n<title>JA1LSY&#45;&gt;N6SKM</title>\n<path fill=\"none\" stroke=\"black\" d=\"M1061.32,-426.22C1061.39,-426.23 1061.46,-426.24 1061.53,-426.25\"/>\n<polygon fill=\"black\" stroke=\"black\" points=\"1051.32,-428.21 1061.74,-426.28 1052.39,-421.29 1051.32,-428.21\"/>\n</g>\n<!-- WB7DD -->\n<g id=\"node21\" class=\"node\">\n<title>WB7DD</title>\n<ellipse fill=\"bisque\" stroke=\"black\" cx=\"992.01\" cy=\"-348\" rx=\"45.23\" ry=\"18\"/>\n<text text-anchor=\"middle\" x=\"992.01\" y=\"-343.8\" font-family=\"Times,serif\" font-size=\"14.00\">WB7DD</text>\n</g>\n<!-- JA1LSY&#45;&gt;WB7DD -->\n<g id=\"edge15\" class=\"edge\">\n<title>JA1LSY&#45;&gt;WB7DD</title>\n<path fill=\"none\" stroke=\"black\" d=\"M1012.48,-401.62C1009.44,-393.66 1005.81,-384.14 1002.45,-375.34\"/>\n<polygon fill=\"black\" stroke=\"black\" points=\"1005.66,-373.94 998.82,-365.84 999.12,-376.43 1005.66,-373.94\"/>\n</g>\n<!-- W5NMG -->\n<g id=\"node29\" class=\"node\">\n<title>W5NMG</title>\n<ellipse fill=\"bisque\" stroke=\"black\" cx=\"971.51\" cy=\"-479.7\" rx=\"47.51\" ry=\"18\"/>\n<text text-anchor=\"middle\" x=\"971.51\" y=\"-475.5\" font-family=\"Times,serif\" font-size=\"14.00\">W5NMG</text>\n</g>\n<!-- JA1LSY&#45;&gt;W5NMG -->\n<g id=\"edge22\" class=\"edge\">\n<title>JA1LSY&#45;&gt;W5NMG</title>\n<path fill=\"none\" stroke=\"black\" d=\"M1005.54,-437.06C1001.31,-442.36 996.56,-448.31 991.99,-454.04\"/>\n<polygon fill=\"black\" stroke=\"black\" points=\"988.99,-452.18 985.49,-462.18 994.46,-456.55 988.99,-452.18\"/>\n</g>\n<!-- JR7TEQ -->\n<g id=\"node15\" class=\"node\">\n<title>JR7TEQ</title>\n<ellipse fill=\"bisque\" stroke=\"black\" cx=\"690.87\" cy=\"-401.7\" rx=\"44.66\" ry=\"18\"/>\n<text text-anchor=\"middle\" x=\"690.87\" y=\"-397.5\" font-family=\"Times,serif\" font-size=\"14.00\">JR7TEQ</text>\n</g>\n<!-- JR7TEQ&#45;&gt;VA7AMV -->\n<g id=\"edge10\" class=\"edge\">\n<title>JR7TEQ&#45;&gt;VA7AMV</title>\n<path fill=\"none\" stroke=\"black\" d=\"M685.03,-419.63C680.66,-433.05 674.61,-451.66 669.62,-466.99\"/>\n<polygon fill=\"black\" stroke=\"black\" points=\"666.29,-465.91 666.53,-476.5 672.95,-468.07 666.29,-465.91\"/>\n</g>\n<!-- VK6YM -->\n<g id=\"node28\" class=\"node\">\n<title>VK6YM</title>\n<ellipse fill=\"bisque\" stroke=\"black\" cx=\"739.69\" cy=\"-330.63\" rx=\"45.23\" ry=\"18\"/>\n<text text-anchor=\"middle\" x=\"739.69\" y=\"-326.43\" font-family=\"Times,serif\" font-size=\"14.00\">VK6YM</text>\n</g>\n<!-- JR7TEQ&#45;&gt;VK6YM -->\n<g id=\"edge30\" class=\"edge\">\n<title>JR7TEQ&#45;&gt;VK6YM</title>\n<path fill=\"none\" stroke=\"black\" d=\"M702.93,-384.13C708.58,-375.91 715.43,-365.94 721.67,-356.85\"/>\n<polygon fill=\"black\" stroke=\"black\" points=\"724.64,-358.71 727.42,-348.49 718.87,-354.75 724.64,-358.71\"/>\n</g>\n<!-- VE6YZ -->\n<g id=\"node47\" class=\"node\">\n<title>VE6YZ</title>\n<ellipse fill=\"bisque\" stroke=\"black\" cx=\"644.05\" cy=\"-333.97\" rx=\"41.71\" ry=\"18\"/>\n<text text-anchor=\"middle\" x=\"644.05\" y=\"-329.77\" font-family=\"Times,serif\" font-size=\"14.00\">VE6YZ</text>\n</g>\n<!-- JR7TEQ&#45;&gt;VE6YZ -->\n<g id=\"edge42\" class=\"edge\">\n<title>JR7TEQ&#45;&gt;VE6YZ</title>\n<path fill=\"none\" stroke=\"black\" d=\"M678.81,-384.26C673.72,-376.89 667.68,-368.15 662.07,-360.04\"/>\n<polygon fill=\"black\" stroke=\"black\" points=\"664.79,-357.82 656.23,-351.59 659.03,-361.8 664.79,-357.82\"/>\n</g>\n<!-- JP1LRT -->\n<g id=\"node24\" class=\"node\">\n<title>JP1LRT</title>\n<ellipse fill=\"bisque\" stroke=\"black\" cx=\"191.34\" cy=\"-628.64\" rx=\"43.46\" ry=\"18\"/>\n<text text-anchor=\"middle\" x=\"191.34\" y=\"-624.44\" font-family=\"Times,serif\" font-size=\"14.00\">JP1LRT</text>\n</g>\n<!-- KQ5U -->\n<g id=\"node25\" class=\"node\">\n<title>KQ5U</title>\n<ellipse fill=\"bisque\" stroke=\"black\" cx=\"119.02\" cy=\"-642.27\" rx=\"36.56\" ry=\"18\"/>\n<text text-anchor=\"middle\" x=\"119.02\" y=\"-638.07\" font-family=\"Times,serif\" font-size=\"14.00\">KQ5U</text>\n</g>\n<!-- JP1LRT&#45;&gt;KQ5U -->\n<g id=\"edge18\" class=\"edge\">\n<title>JP1LRT&#45;&gt;KQ5U</title>\n<path fill=\"none\" stroke=\"black\" d=\"M151.8,-636.1C151.73,-636.11 151.67,-636.12 151.6,-636.13\"/>\n<polygon fill=\"black\" stroke=\"black\" points=\"160.58,-630.87 151.4,-636.17 161.88,-637.75 160.58,-630.87\"/>\n</g>\n<!-- N7ND -->\n<g id=\"node52\" class=\"node\">\n<title>N7ND</title>\n<ellipse fill=\"bisque\" stroke=\"black\" cx=\"266.2\" cy=\"-614.96\" rx=\"36.56\" ry=\"18\"/>\n<text text-anchor=\"middle\" x=\"266.2\" y=\"-610.76\" font-family=\"Times,serif\" font-size=\"14.00\">N7ND</text>\n</g>\n<!-- JP1LRT&#45;&gt;N7ND -->\n<g id=\"edge46\" class=\"edge\">\n<title>JP1LRT&#45;&gt;N7ND</title>\n<path fill=\"none\" stroke=\"black\" d=\"M230.96,-621.4C231.03,-621.39 231.1,-621.37 231.17,-621.36\"/>\n<polygon fill=\"black\" stroke=\"black\" points=\"222.18,-626.57 231.38,-621.32 220.91,-619.68 222.18,-626.57\"/>\n</g>\n<!-- K7GQ -->\n<g id=\"node27\" class=\"node\">\n<title>K7GQ</title>\n<ellipse fill=\"bisque\" stroke=\"black\" cx=\"765.7\" cy=\"-250.66\" rx=\"36.56\" ry=\"18\"/>\n<text text-anchor=\"middle\" x=\"765.7\" y=\"-246.46\" font-family=\"Times,serif\" font-size=\"14.00\">K7GQ</text>\n</g>\n<!-- K7GQ&#45;&gt;VK6YM -->\n<g id=\"edge20\" class=\"edge\">\n<title>K7GQ&#45;&gt;VK6YM</title>\n<path fill=\"none\" stroke=\"black\" d=\"M759.8,-268.8C756.54,-278.82 752.42,-291.48 748.76,-302.73\"/>\n<polygon fill=\"black\" stroke=\"black\" points=\"745.33,-301.96 745.57,-312.55 751.99,-304.13 745.33,-301.96\"/>\n</g>\n<!-- JR1WCS -->\n<g id=\"node32\" class=\"node\">\n<title>JR1WCS</title>\n<ellipse fill=\"bisque\" stroke=\"black\" cx=\"844.66\" cy=\"-227.76\" rx=\"46.97\" ry=\"18\"/>\n<text text-anchor=\"middle\" x=\"844.66\" y=\"-223.56\" font-family=\"Times,serif\" font-size=\"14.00\">JR1WCS</text>\n</g>\n<!-- K7GQ&#45;&gt;JR1WCS -->\n<g id=\"edge24\" class=\"edge\">\n<title>K7GQ&#45;&gt;JR1WCS</title>\n<path fill=\"none\" stroke=\"black\" d=\"M797.36,-241.48C797.46,-241.45 797.56,-241.42 797.66,-241.39\"/>\n<polygon fill=\"black\" stroke=\"black\" points=\"798.38,-244.83 807.01,-238.68 796.43,-238.1 798.38,-244.83\"/>\n</g>\n<!-- JR2BYJ -->\n<g id=\"node39\" class=\"node\">\n<title>JR2BYJ</title>\n<ellipse fill=\"bisque\" stroke=\"black\" cx=\"745.65\" cy=\"-170.01\" rx=\"43.46\" ry=\"18\"/>\n<text text-anchor=\"middle\" x=\"745.65\" y=\"-165.81\" font-family=\"Times,serif\" font-size=\"14.00\">JR2BYJ</text>\n</g>\n<!-- K7GQ&#45;&gt;JR2BYJ -->\n<g id=\"edge31\" class=\"edge\">\n<title>K7GQ&#45;&gt;JR2BYJ</title>\n<path fill=\"none\" stroke=\"black\" d=\"M761.25,-232.76C758.73,-222.6 755.51,-209.65 752.65,-198.16\"/>\n<polygon fill=\"black\" stroke=\"black\" points=\"755.97,-196.99 750.16,-188.13 749.17,-198.68 755.97,-196.99\"/>\n</g>\n<!-- JA1DKT -->\n<g id=\"node30\" class=\"node\">\n<title>JA1DKT</title>\n<ellipse fill=\"bisque\" stroke=\"black\" cx=\"1023.95\" cy=\"-1011.31\" rx=\"46.37\" ry=\"18\"/>\n<text text-anchor=\"middle\" x=\"1023.95\" y=\"-1007.11\" font-family=\"Times,serif\" font-size=\"14.00\">JA1DKT</text>\n</g>\n<!-- JA1DKT&#45;&gt;N5XJ -->\n<g id=\"edge52\" class=\"edge\">\n<title>JA1DKT&#45;&gt;N5XJ</title>\n<path fill=\"none\" stroke=\"black\" d=\"M1022.04,-992.9C1020.54,-978.46 1018.42,-958.11 1016.71,-941.62\"/>\n<polygon fill=\"black\" stroke=\"black\" points=\"1020.17,-941.03 1015.65,-931.44 1013.2,-941.75 1020.17,-941.03\"/>\n</g>\n<!-- VA7PSK -->\n<g id=\"node31\" class=\"node\">\n<title>VA7PSK</title>\n<ellipse fill=\"bisque\" stroke=\"black\" cx=\"1042.93\" cy=\"-1090.11\" rx=\"47.53\" ry=\"18\"/>\n<text text-anchor=\"middle\" x=\"1042.93\" y=\"-1085.91\" font-family=\"Times,serif\" font-size=\"14.00\">VA7PSK</text>\n</g>\n<!-- JA1DKT&#45;&gt;VA7PSK -->\n<g id=\"edge23\" class=\"edge\">\n<title>JA1DKT&#45;&gt;VA7PSK</title>\n<path fill=\"none\" stroke=\"black\" d=\"M1028.35,-1029.59C1030.68,-1039.23 1033.58,-1051.28 1036.18,-1062.08\"/>\n<polygon fill=\"black\" stroke=\"black\" points=\"1032.81,-1063.03 1038.55,-1071.93 1039.61,-1061.39 1032.81,-1063.03\"/>\n</g>\n<!-- JH1KAK -->\n<g id=\"node33\" class=\"node\">\n<title>JH1KAK</title>\n<ellipse fill=\"bisque\" stroke=\"black\" cx=\"509.51\" cy=\"-886.64\" rx=\"47.51\" ry=\"18\"/>\n<text text-anchor=\"middle\" x=\"509.51\" y=\"-882.44\" font-family=\"Times,serif\" font-size=\"14.00\">JH1KAK</text>\n</g>\n<!-- K6GZ -->\n<g id=\"node34\" class=\"node\">\n<title>K6GZ</title>\n<ellipse fill=\"bisque\" stroke=\"black\" cx=\"580.72\" cy=\"-876\" rx=\"35.92\" ry=\"18\"/>\n<text text-anchor=\"middle\" x=\"580.72\" y=\"-871.8\" font-family=\"Times,serif\" font-size=\"14.00\">K6GZ</text>\n</g>\n<!-- JH1KAK&#45;&gt;K6GZ -->\n<g id=\"edge25\" class=\"edge\">\n<title>JH1KAK&#45;&gt;K6GZ</title>\n<path fill=\"none\" stroke=\"black\" d=\"M553.79,-880.02C553.85,-880.01 553.91,-880.01 553.96,-880\"/>\n<polygon fill=\"black\" stroke=\"black\" points=\"544.76,-884.92 554.13,-879.97 543.72,-877.99 544.76,-884.92\"/>\n</g>\n<!-- JR2AMZ -->\n<g id=\"node35\" class=\"node\">\n<title>JR2AMZ</title>\n<ellipse fill=\"bisque\" stroke=\"black\" cx=\"47.52\" cy=\"-656.08\" rx=\"47.53\" ry=\"18\"/>\n<text text-anchor=\"middle\" x=\"47.52\" y=\"-651.88\" font-family=\"Times,serif\" font-size=\"14.00\">JR2AMZ</text>\n</g>\n<!-- JR2AMZ&#45;&gt;KQ5U -->\n<g id=\"edge26\" class=\"edge\">\n<title>JR2AMZ&#45;&gt;KQ5U</title>\n<path fill=\"none\" stroke=\"black\" d=\"M89.94,-647.89C90,-647.88 90.06,-647.86 90.12,-647.85\"/>\n<polygon fill=\"black\" stroke=\"black\" points=\"81.14,-653.15 90.3,-647.82 79.81,-646.28 81.14,-653.15\"/>\n</g>\n<!-- JH1LZU -->\n<g id=\"node37\" class=\"node\">\n<title>JH1LZU</title>\n<ellipse fill=\"bisque\" stroke=\"black\" cx=\"762.59\" cy=\"-710.54\" rx=\"45.22\" ry=\"18\"/>\n<text text-anchor=\"middle\" x=\"762.59\" y=\"-706.34\" font-family=\"Times,serif\" font-size=\"14.00\">JH1LZU</text>\n</g>\n<!-- JH1LZU&#45;&gt;VE6WQ -->\n<g id=\"edge28\" class=\"edge\">\n<title>JH1LZU&#45;&gt;VE6WQ</title>\n<path fill=\"none\" stroke=\"black\" d=\"M745.97,-693.63C739.05,-686.59 730.88,-678.29 723.33,-670.61\"/>\n<polygon fill=\"black\" stroke=\"black\" points=\"725.56,-667.89 716.06,-663.21 720.57,-672.79 725.56,-667.89\"/>\n</g>\n<!-- JH1LZU&#45;&gt;LU8VLE -->\n<g id=\"edge36\" class=\"edge\">\n<title>JH1LZU&#45;&gt;LU8VLE</title>\n<path fill=\"none\" stroke=\"black\" d=\"M769.05,-728.47C772.95,-739.3 778,-753.32 782.4,-765.54\"/>\n<polygon fill=\"black\" stroke=\"black\" points=\"779.23,-767.06 785.91,-775.28 785.81,-764.68 779.23,-767.06\"/>\n</g>\n<!-- KJ4GK -->\n<g id=\"node46\" class=\"node\">\n<title>KJ4GK</title>\n<ellipse fill=\"bisque\" stroke=\"black\" cx=\"835.69\" cy=\"-674.36\" rx=\"40.57\" ry=\"18\"/>\n<text text-anchor=\"middle\" x=\"835.69\" y=\"-670.16\" font-family=\"Times,serif\" font-size=\"14.00\">KJ4GK</text>\n</g>\n<!-- JH1LZU&#45;&gt;KJ4GK -->\n<g id=\"edge41\" class=\"edge\">\n<title>JH1LZU&#45;&gt;KJ4GK</title>\n<path fill=\"none\" stroke=\"black\" d=\"M791.07,-696.45C793.86,-695.06 796.73,-693.65 799.58,-692.23\"/>\n<polygon fill=\"black\" stroke=\"black\" points=\"801.21,-695.33 808.62,-687.76 798.1,-689.06 801.21,-695.33\"/>\n</g>\n<!-- PY5ZHP -->\n<g id=\"node48\" class=\"node\">\n<title>PY5ZHP</title>\n<ellipse fill=\"bisque\" stroke=\"black\" cx=\"747.67\" cy=\"-92.61\" rx=\"46.39\" ry=\"18\"/>\n<text text-anchor=\"middle\" x=\"747.67\" y=\"-88.41\" font-family=\"Times,serif\" font-size=\"14.00\">PY5ZHP</text>\n</g>\n<!-- JR2BYJ&#45;&gt;PY5ZHP -->\n<g id=\"edge43\" class=\"edge\">\n<title>JR2BYJ&#45;&gt;PY5ZHP</title>\n<path fill=\"none\" stroke=\"black\" d=\"M746.13,-151.66C746.37,-142.51 746.66,-131.23 746.93,-120.99\"/>\n<polygon fill=\"black\" stroke=\"black\" points=\"750.43,-120.91 747.19,-110.82 743.43,-120.73 750.43,-120.91\"/>\n</g>\n<!-- JA4VUQ -->\n<g id=\"node40\" class=\"node\">\n<title>JA4VUQ</title>\n<ellipse fill=\"bisque\" stroke=\"black\" cx=\"1079.9\" cy=\"-922.02\" rx=\"47.51\" ry=\"18\"/>\n<text text-anchor=\"middle\" x=\"1079.9\" y=\"-917.82\" font-family=\"Times,serif\" font-size=\"14.00\">JA4VUQ</text>\n</g>\n<!-- JA4VUQ&#45;&gt;N5XJ -->\n<g id=\"edge32\" class=\"edge\">\n<title>JA4VUQ&#45;&gt;N5XJ</title>\n<path fill=\"none\" stroke=\"black\" d=\"M1034.7,-916.16C1034.66,-916.15 1034.61,-916.15 1034.57,-916.14\"/>\n<polygon fill=\"black\" stroke=\"black\" points=\"1044.8,-913.95 1034.43,-916.13 1043.9,-920.89 1044.8,-913.95\"/>\n</g>\n<!-- JA9CAC -->\n<g id=\"node41\" class=\"node\">\n<title>JA9CAC</title>\n<ellipse fill=\"bisque\" stroke=\"black\" cx=\"676.05\" cy=\"-713.91\" rx=\"46.39\" ry=\"18\"/>\n<text text-anchor=\"middle\" x=\"676.05\" y=\"-709.71\" font-family=\"Times,serif\" font-size=\"14.00\">JA9CAC</text>\n</g>\n<!-- JA9CAC&#45;&gt;VE6WQ -->\n<g id=\"edge33\" class=\"edge\">\n<title>JA9CAC&#45;&gt;VE6WQ</title>\n<path fill=\"none\" stroke=\"black\" d=\"M682.28,-695.77C684.58,-689.09 687.24,-681.36 689.76,-674.02\"/>\n<polygon fill=\"black\" stroke=\"black\" points=\"693.13,-674.99 693.07,-664.39 686.51,-672.71 693.13,-674.99\"/>\n</g>\n<!-- JA8NDB -->\n<g id=\"node49\" class=\"node\">\n<title>JA8NDB</title>\n<ellipse fill=\"bisque\" stroke=\"black\" cx=\"731.6\" cy=\"-848.73\" rx=\"46.95\" ry=\"18\"/>\n<text text-anchor=\"middle\" x=\"731.6\" y=\"-844.53\" font-family=\"Times,serif\" font-size=\"14.00\">JA8NDB</text>\n</g>\n<!-- JA8NDB&#45;&gt;LU8VLE -->\n<g id=\"edge44\" class=\"edge\">\n<title>JA8NDB&#45;&gt;LU8VLE</title>\n<path fill=\"none\" stroke=\"black\" d=\"M749.83,-832.06C755.11,-827.22 760.99,-821.85 766.64,-816.68\"/>\n<polygon fill=\"black\" stroke=\"black\" points=\"769.12,-819.16 774.14,-809.83 764.4,-813.99 769.12,-819.16\"/>\n</g>\n<!-- JA7QVI -->\n<g id=\"node50\" class=\"node\">\n<title>JA7QVI</title>\n<ellipse fill=\"bisque\" stroke=\"black\" cx=\"342.63\" cy=\"-603.07\" rx=\"44\" ry=\"18\"/>\n<text text-anchor=\"middle\" x=\"342.63\" y=\"-598.87\" font-family=\"Times,serif\" font-size=\"14.00\">JA7QVI</text>\n</g>\n<!-- HC1KX -->\n<g id=\"node51\" class=\"node\">\n<title>HC1KX</title>\n<ellipse fill=\"bisque\" stroke=\"black\" cx=\"294.41\" cy=\"-528.76\" rx=\"43.44\" ry=\"18\"/>\n<text text-anchor=\"middle\" x=\"294.41\" y=\"-524.56\" font-family=\"Times,serif\" font-size=\"14.00\">HC1KX</text>\n</g>\n<!-- JA7QVI&#45;&gt;HC1KX -->\n<g id=\"edge45\" class=\"edge\">\n<title>JA7QVI&#45;&gt;HC1KX</title>\n<path fill=\"none\" stroke=\"black\" d=\"M331.2,-585.46C325.26,-576.3 317.87,-564.92 311.29,-554.77\"/>\n<polygon fill=\"black\" stroke=\"black\" points=\"314.14,-552.73 305.76,-546.25 308.26,-556.54 314.14,-552.73\"/>\n</g>\n<!-- JA7QVI&#45;&gt;N7ND -->\n<g id=\"edge55\" class=\"edge\">\n<title>JA7QVI&#45;&gt;N7ND</title>\n<path fill=\"none\" stroke=\"black\" d=\"M301.28,-609.5C301.21,-609.51 301.14,-609.52 301.07,-609.53\"/>\n<polygon fill=\"black\" stroke=\"black\" points=\"310.2,-604.57 300.86,-609.57 311.28,-611.48 310.2,-604.57\"/>\n</g>\n<!-- JA7QVI&#45;&gt;PY2ABA -->\n<g id=\"edge49\" class=\"edge\">\n<title>JA7QVI&#45;&gt;PY2ABA</title>\n<path fill=\"none\" stroke=\"black\" d=\"M383.99,-596.75C384.07,-596.74 384.15,-596.73 384.23,-596.71\"/>\n<polygon fill=\"black\" stroke=\"black\" points=\"375.12,-601.65 384.48,-596.68 374.06,-594.73 375.12,-601.65\"/>\n</g>\n<!-- HC1Y -->\n<g id=\"node61\" class=\"node\">\n<title>HC1Y</title>\n<ellipse fill=\"bisque\" stroke=\"black\" cx=\"315.67\" cy=\"-685.75\" rx=\"36.5\" ry=\"18\"/>\n<text text-anchor=\"middle\" x=\"315.67\" y=\"-681.55\" font-family=\"Times,serif\" font-size=\"14.00\">HC1Y</text>\n</g>\n<!-- JA7QVI&#45;&gt;HC1Y -->\n<g id=\"edge57\" class=\"edge\">\n<title>JA7QVI&#45;&gt;HC1Y</title>\n<path fill=\"none\" stroke=\"black\" d=\"M336.78,-621.01C333.25,-631.84 328.67,-645.88 324.68,-658.11\"/>\n<polygon fill=\"black\" stroke=\"black\" points=\"321.28,-657.25 321.51,-667.85 327.94,-659.42 321.28,-657.25\"/>\n</g>\n<!-- JH8OCV -->\n<g id=\"node53\" class=\"node\">\n<title>JH8OCV</title>\n<ellipse fill=\"bisque\" stroke=\"black\" cx=\"1101.22\" cy=\"-871.8\" rx=\"46.95\" ry=\"18\"/>\n<text text-anchor=\"middle\" x=\"1101.22\" y=\"-867.6\" font-family=\"Times,serif\" font-size=\"14.00\">JH8OCV</text>\n</g>\n<!-- JH8OCV&#45;&gt;N5XJ -->\n<g id=\"edge51\" class=\"edge\">\n<title>JH8OCV&#45;&gt;N5XJ</title>\n<path fill=\"none\" stroke=\"black\" d=\"M1071.62,-885.9C1064.08,-889.49 1055.91,-893.38 1048.16,-897.07\"/>\n<polygon fill=\"black\" stroke=\"black\" points=\"1046.5,-893.99 1038.98,-901.45 1049.51,-900.31 1046.5,-893.99\"/>\n</g>\n<!-- 3G3G -->\n<g id=\"node54\" class=\"node\">\n<title>3G3G</title>\n<ellipse fill=\"bisque\" stroke=\"black\" cx=\"1182.05\" cy=\"-863.56\" rx=\"34.77\" ry=\"18\"/>\n<text text-anchor=\"middle\" x=\"1182.05\" y=\"-859.36\" font-family=\"Times,serif\" font-size=\"14.00\">3G3G</text>\n</g>\n<!-- JH8OCV&#45;&gt;3G3G -->\n<g id=\"edge47\" class=\"edge\">\n<title>JH8OCV&#45;&gt;3G3G</title>\n<path fill=\"none\" stroke=\"black\" d=\"M1146.83,-867.15C1146.97,-867.14 1147.12,-867.12 1147.26,-867.11\"/>\n<polygon fill=\"black\" stroke=\"black\" points=\"1138.1,-871.56 1147.69,-867.06 1137.38,-864.6 1138.1,-871.56\"/>\n</g>\n<!-- UA0JFG -->\n<g id=\"node57\" class=\"node\">\n<title>UA0JFG</title>\n<ellipse fill=\"bisque\" stroke=\"black\" cx=\"1257.88\" cy=\"-869.85\" rx=\"45.81\" ry=\"18\"/>\n<text text-anchor=\"middle\" x=\"1257.88\" y=\"-865.65\" font-family=\"Times,serif\" font-size=\"14.00\">UA0JFG</text>\n</g>\n<!-- UA0JFG&#45;&gt;3G3G -->\n<g id=\"edge50\" class=\"edge\">\n<title>UA0JFG&#45;&gt;3G3G</title>\n<path fill=\"none\" stroke=\"black\" d=\"M1212.89,-866.12C1212.83,-866.11 1212.77,-866.11 1212.7,-866.1\"/>\n<polygon fill=\"black\" stroke=\"black\" points=\"1222.77,-863.43 1212.51,-866.09 1222.19,-870.41 1222.77,-863.43\"/>\n</g>\n<!-- JR7GBL -->\n<g id=\"node59\" class=\"node\">\n<title>JR7GBL</title>\n<ellipse fill=\"bisque\" stroke=\"black\" cx=\"752.61\" cy=\"-18\" rx=\"45.24\" ry=\"18\"/>\n<text text-anchor=\"middle\" x=\"752.61\" y=\"-13.8\" font-family=\"Times,serif\" font-size=\"14.00\">JR7GBL</text>\n</g>\n<!-- JR7GBL&#45;&gt;PY5ZHP -->\n<g id=\"edge54\" class=\"edge\">\n<title>JR7GBL&#45;&gt;PY5ZHP</title>\n<path fill=\"none\" stroke=\"black\" d=\"M751.41,-36.06C750.85,-44.52 750.17,-54.8 749.54,-64.26\"/>\n<polygon fill=\"black\" stroke=\"black\" points=\"746.04,-64.25 748.87,-74.46 753.02,-64.71 746.04,-64.25\"/>\n</g>\n<!-- JH2WDT -->\n<g id=\"node63\" class=\"node\">\n<title>JH2WDT</title>\n<ellipse fill=\"bisque\" stroke=\"black\" cx=\"651.02\" cy=\"-466.96\" rx=\"48.66\" ry=\"18\"/>\n<text text-anchor=\"middle\" x=\"651.02\" y=\"-462.76\" font-family=\"Times,serif\" font-size=\"14.00\">JH2WDT</text>\n</g>\n<!-- JH2WDT&#45;&gt;K7CTV -->\n<g id=\"edge62\" class=\"edge\">\n<title>JH2WDT&#45;&gt;K7CTV</title>\n<path fill=\"none\" stroke=\"black\" d=\"M681.83,-480.98C690.25,-484.81 699.49,-489.01 708.29,-493.02\"/>\n<polygon fill=\"black\" stroke=\"black\" points=\"707.05,-496.3 717.6,-497.26 709.94,-489.93 707.05,-496.3\"/>\n</g>\n<!-- JH2WDT&#45;&gt;KB7FD -->\n<g id=\"edge59\" class=\"edge\">\n<title>JH2WDT&#45;&gt;KB7FD</title>\n<path fill=\"none\" stroke=\"black\" d=\"M617.38,-480.24C615.24,-481.08 613.08,-481.93 610.92,-482.79\"/>\n<polygon fill=\"black\" stroke=\"black\" points=\"609.55,-479.57 601.53,-486.49 612.12,-486.08 609.55,-479.57\"/>\n</g>\n<!-- JR3UIC -->\n<g id=\"node65\" class=\"node\">\n<title>JR3UIC</title>\n<ellipse fill=\"bisque\" stroke=\"black\" cx=\"535.08\" cy=\"-751.97\" rx=\"42.88\" ry=\"18\"/>\n<text text-anchor=\"middle\" x=\"535.08\" y=\"-747.77\" font-family=\"Times,serif\" font-size=\"14.00\">JR3UIC</text>\n</g>\n<!-- JR3UIC&#45;&gt;AA4M -->\n<g id=\"edge61\" class=\"edge\">\n<title>JR3UIC&#45;&gt;AA4M</title>\n<path fill=\"none\" stroke=\"black\" d=\"M545.28,-734.4C550.77,-724.94 557.66,-713.08 563.78,-702.54\"/>\n<polygon fill=\"black\" stroke=\"black\" points=\"566.91,-704.11 568.91,-693.71 560.86,-700.6 566.91,-704.11\"/>\n</g>\n</g>\n</svg>\n"
    }
  ],
  "journal": [
    {
      "type": "fork",
      "date": 1605831445311
    }
  ]
}